Metadata-Version: 1.1
Name: ymgcounter
Version: 0.0.1
Summary: very basic counter
Home-page: UNKNOWN
Author: Yam
Author-email: ymgchbrtv0095@gmail.com
License: MIT
Keywords: math,counter
Platform: UNKNOWN
Classifier: Development Status :: 5 - Production/Stable
Classifier: Intended Audience :: Education
Classifier: Operating System :: OS Independent
Classifier: License :: OSI Approved :: MIT License
Classifier: Programming Language :: Python :: 3
